toggl_invoice_generator/__init__.py
toggl_invoice_generator/__main__.py
toggl_invoice_generator/analyze.py
toggl_invoice_generator/config.py
toggl_invoice_generator/invoice.py
toggl_invoice_generator/toggl.py
toggl_invoice_gen-0.1.3.dist-info/METADATA
toggl_invoice_gen-0.1.3.dist-info/WHEEL
toggl_invoice_gen-0.1.3.dist-info/entry_points.txt
toggl_invoice_gen-0.1.3.dist-info/licenses/LICENSE
toggl_invoice_gen-0.1.3.dist-info/RECORD
