Metadata-Version: 2.4
Name: toggl-invoice-gen
Version: 0.1.3
Summary: Take a mapping of Toggl Track projects and manually inputted rates, download a report, and generate an invoice
Author-email: slashtechno <77907286+slashtechno@users.noreply.github.com>
License-File: LICENSE
Requires-Python: >=3.13
Requires-Dist: httpx>=0.28.1
Requires-Dist: loguru>=0.7.3
Requires-Dist: pydantic-settings>=2.10.1
Requires-Dist: pydantic>=2.11.7
Requires-Dist: python-decouple>=3.8
Requires-Dist: reportlab>=4.0.0
